posit/envar_encrypter/envar_encrypter.py
posit-pass/encrypter.py
posit_pass/encrypt.py
posit_pass/encrypter.py
posit_pass_encrypt-1.0.0.dist-info/METADATA
posit_pass_encrypt-1.0.0.dist-info/WHEEL
posit_pass_encrypt-1.0.0.dist-info/top_level.txt
posit_pass_encrypt-1.0.0.dist-info/RECORD
