Metadata-Version: 2.1
Name: posit-pass-encrypt
Version: 1.0.0
Summary: POSIT Environment Variables Encrypter
Home-page: UNKNOWN
License: Other/Proprietary License
Platform: any
Classifier: License :: Other/Proprietary License
Classifier: Natural Language :: English
Classifier: Operating System :: OS Independent
Classifier: Programming Language :: Python :: 3 :: Only
Classifier: Programming Language :: Python :: 3.7
Classifier: Programming Language :: Python :: 3.8
Classifier: Programming Language :: Python :: 3.9
Classifier: Programming Language :: Python :: 3.10
Requires-Python: <3.11,>=3.7
Requires-Dist: cryptography
Requires-Dist: getpass4
